CHANGES
MANIFEST.in
README
setup.cfg
setup.py
ZSI/ServiceContainer.py
ZSI/ServiceProxy.py
ZSI/TC.py
ZSI/TCapache.py
ZSI/TCcompound.py
ZSI/TCnumbers.py
ZSI/TCtimes.py
ZSI/__init__.py
ZSI/address.py
ZSI/auth.py
ZSI/client.py
ZSI/digest_auth.py
ZSI/dispatch.py
ZSI/fault.py
ZSI/parse.py
ZSI/resolvers.py
ZSI/schema.py
ZSI/typeinterpreter.py
ZSI/version.py
ZSI/writer.py
ZSI/generate/__init__.py
ZSI/generate/commands.py
ZSI/generate/containers.py
ZSI/generate/pyclass.py
ZSI/generate/utility.py
ZSI/generate/wsdl2dispatch.py
ZSI/generate/wsdl2python.py
ZSI/twisted/WSresource.py
ZSI/twisted/WSsecurity.py
ZSI/twisted/__init__.py
ZSI/twisted/client.py
ZSI/twisted/interfaces.py
ZSI/twisted/reverse.py
ZSI/twisted/wsgi.py
ZSI/wstools/Namespaces.py
ZSI/wstools/TimeoutSocket.py
ZSI/wstools/UserTuple.py
ZSI/wstools/Utility.py
ZSI/wstools/WSDLTools.py
ZSI/wstools/XMLSchema.py
ZSI/wstools/XMLname.py
ZSI/wstools/__init__.py
ZSI/wstools/c14n.py
ZSI/wstools/logging.py
ZSI/wstools/test/__init__.py
ZSI/wstools/test/test_t1.py
ZSI/wstools/test/test_wsdl.py
ZSI/wstools/test/test_wstools.py
ZSI/wstools/test/test_wstools_net.py
doc/.cvsignore
doc/Makefile
doc/app-dispatch-dict.tex
doc/app-dispatch.tex
doc/app-lowlevel.tex
doc/app-pickler.tex
doc/bibliography.tex
doc/blank.png
doc/c01-intro.tex
doc/c02-samples.tex
doc/c02a-coverage.tex
doc/c03-except.tex
doc/c04-utils.tex
doc/c05-parse.tex
doc/c06-tc.tex
doc/c07-writer.tex
doc/c08-fault.tex
doc/c09-resolve.tex
doc/c10-dispatch.tex
doc/client-hello-struct.tex
doc/contents.png
doc/dispatch-rpc-hello-array.tex
doc/dispatch-rpc-hello-struct.tex
doc/guide.css
doc/guide.html
doc/guide.pdf
doc/guide.ps
doc/guide.tex
doc/guide01-intro.tex
doc/guide02-wsdl2py.tex
doc/index.png
doc/modules.png
doc/next.png
doc/previous.png
doc/pyfav.png
doc/up.png
doc/version.tex
doc/zsi.css
doc/zsi.html
doc/zsi.l2h~
doc/zsi.pdf
doc/zsi.ps
doc/zsi.tex
doc/zsi.xsd
doc/examples/client/receive_response/complex/binding.wsdl
m3_ZSI.egg-info/PKG-INFO
m3_ZSI.egg-info/SOURCES.txt
m3_ZSI.egg-info/dependency_links.txt
m3_ZSI.egg-info/entry_points.txt
m3_ZSI.egg-info/requires.txt
m3_ZSI.egg-info/top_level.txt
